setup.cfg
setup.py
sasvenv/__init__.py
sasvenv/sasvenv.py
sasvenv.egg-info/PKG-INFO
sasvenv.egg-info/SOURCES.txt
sasvenv.egg-info/dependency_links.txt
sasvenv.egg-info/not-zip-safe
sasvenv.egg-info/top_level.txt