Metadata-Version: 2.1
Name: sasvenv
Version: 0.2
Summary: Модуль для более быстрого создания venv
Home-page: UNKNOWN
Author-email: kassas20@mail.ru
License: UNKNOWN
Platform: UNKNOWN
